commons/__init__.py
commons/admin.py
commons/apps.py
commons/exception_handler.py
commons/functions.py
commons/models.py
commons/pagination.py
commons/permissions.py
commons/serializers.py
commons/tests.py
commons/urls.py
commons/utils.py
commons/views.py
commons/migrations/0001_initial.py
commons/migrations/0002_auto_20210611_1558.py
commons/migrations/__init__.py
commons/mixins/__init__.py
commons/mixins/viewsets.py
insight_workshop_commons-0.10.dist-info/LICENSE
insight_workshop_commons-0.10.dist-info/METADATA
insight_workshop_commons-0.10.dist-info/WHEEL
insight_workshop_commons-0.10.dist-info/top_level.txt
insight_workshop_commons-0.10.dist-info/RECORD
